{
  "janeiro": {
    "faturamento": 2760.0,
    "vendas": 37,
    "clientes": 26,
    "changeVendas": 0,
    "changeFaturamento": 0,
    "changeTicket": 0,
    "changeClientes": 0,
    "servicos": [
      {
        "nome": "Progressiva",
        "faturamento": 890.0
      },
      {
        "nome": "Coloração",
        "faturamento": 370.0
      },
      {
        "nome": "escova",
        "faturamento": 315.0
      },
      {
        "nome": "Corte + escova",
        "faturamento": 255.0
      },
      {
        "nome": "coloração + hidrat",
        "faturamento": 200.0
      },
      {
        "nome": "hidratação",
        "faturamento": 180.0
      },
      {
        "nome": "corte",
        "faturamento": 120.0
      },
      {
        "nome": "manicure + pedicure",
        "faturamento": 110.0
      },
      {
        "nome": "manicure",
        "faturamento": 90.0
      },
      {
        "nome": "sobrancelha",
        "faturamento": 75.0
      },
      {
        "nome": "corte infantil",
        "faturamento": 70.0
      },
      {
        "nome": "corte + barba",
        "faturamento": 50.0
      },
      {
        "nome": "pedicure",
        "faturamento": 35.0
      }
    ],
    "formas_pagamento": [
      {
        "nome": "PIX",
        "valor": 1440.0
      },
      {
        "nome": "CREDITO",
        "valor": 600.0
      },
      {
        "nome": "DINHEIRO",
        "valor": 540.0
      },
      {
        "nome": "DEBITO",
        "valor": 180.0
      }
    ],
    "atividade_semana": [
      {
        "nome": "Segunda",
        "faturamento": 300.0
      },
      {
        "nome": "Terça",
        "faturamento": 390.0
      },
      {
        "nome": "Quinta",
        "faturamento": 460.0
      },
      {
        "nome": "Sexta",
        "faturamento": 695.0
      },
      {
        "nome": "Sábado",
        "faturamento": 535.0
      },
      {
        "nome": "Domingo",
        "faturamento": 380.0
      }
    ],
    "insights": {
      "atividade_semana": "Sexta-feira gerou R$ 695 — 25% do faturamento total do mês sozinha. Quarta-feira não teve nenhum atendimento registrado. Ação: crie uma promoção 'Quarta da Beleza' com desconto em escova ou sobrancelha. Mesmo 2 atendimentos extras por quarta equivalem a ~R$ 350 a mais por mês.",
      "servicos": "A Progressiva respondeu por 32% do faturamento (R$ 890) — alta concentração em um único serviço representa risco. Se a demanda cair, o impacto é imediato. Ação: ofereça hidratação ou coloração como complemento para quem faz progressiva. Apenas R$ 30 extras por cliente de progressiva somam ~R$ 150/mês adicionais.",
      "formas_pagamento": "PIX + dinheiro somaram 72% dos pagamentos — ótimo para o fluxo de caixa imediato. Cartão de crédito representou 22% (R$ 600). Ação: se você parcela no crédito sem cobrar taxa, avalie aplicar custo de parcelamento a partir de 2x. Isso protege sua margem sem afastar clientes.",
      "faturamento_mes": "Janeiro foi o mês base do ano: R$ 2.760, 37 atendimentos e ticket médio de R$ 74,59. Use esse número como referência para medir crescimento nos meses seguintes. Ação: defina uma meta de crescimento de 10% ao mês — isso levaria o salão a R$ 3.000 em fevereiro.",
      "comparativo_faturamento": "Primeiro mês registrado no sistema — sem histórico anterior para comparar. A partir de fevereiro você verá a variação mês a mês. Ação: guarde todos os CSVs mensais para construir um histórico sólido. Quanto mais meses, mais precisa fica a análise de sazonalidade.",
      "ticket_medio_servico": "Progressiva (~R$ 180) e Coloração (~R$ 120) têm os maiores tickets individuais. Esses são seus serviços âncora. Ação: monte combos como 'Progressiva + Hidratação' ou 'Coloração + Escova'. Oferecer no momento do agendamento aumenta o ticket sem esforço extra de captação.",
      "taxa_recorrencia": "Janeiro com 26 clientes únicos é o ponto de partida para medir fidelidade. Ação: monitore quantos desses 26 retornam em fevereiro. Clientes que voltam em 30 dias têm custo de aquisição zero e são o seu ativo mais valioso."
    }
  },
  "fevereiro": {
    "faturamento": 2180.0,
    "vendas": 26,
    "clientes": 22,
    "changeVendas": -29.7,
    "changeFaturamento": -21.0,
    "changeTicket": 12.4,
    "changeClientes": -15.4,
    "servicos": [
      {
        "nome": "Progressiva",
        "faturamento": 720.0
      },
      {
        "nome": "Coloração",
        "faturamento": 370.0
      },
      {
        "nome": "Corte + escova",
        "faturamento": 255.0
      },
      {
        "nome": "coloração + hidrat",
        "faturamento": 200.0
      },
      {
        "nome": "escova",
        "faturamento": 180.0
      },
      {
        "nome": "hidratação",
        "faturamento": 120.0
      },
      {
        "nome": "manicure + pedicure",
        "faturamento": 110.0
      },
      {
        "nome": "corte",
        "faturamento": 80.0
      },
      {
        "nome": "manicure",
        "faturamento": 60.0
      },
      {
        "nome": "sobrancelha",
        "faturamento": 50.0
      },
      {
        "nome": "corte infantil",
        "faturamento": 35.0
      }
    ],
    "formas_pagamento": [
      {
        "nome": "PIX",
        "valor": 1275.0
      },
      {
        "nome": "CREDITO",
        "valor": 535.0
      },
      {
        "nome": "DINHEIRO",
        "valor": 370.0
      }
    ],
    "atividade_semana": [
      {
        "nome": "Segunda",
        "faturamento": 260.0
      },
      {
        "nome": "Terça",
        "faturamento": 335.0
      },
      {
        "nome": "Quinta",
        "faturamento": 395.0
      },
      {
        "nome": "Sexta",
        "faturamento": 335.0
      },
      {
        "nome": "Sábado",
        "faturamento": 460.0
      },
      {
        "nome": "Domingo",
        "faturamento": 395.0
      }
    ],
    "insights": {
      "atividade_semana": "Sábado assumiu a liderança (R$ 460) e quarta novamente sem atendimentos — segundo mês seguido. Ação: crie uma ação 'Quarta da Beleza' com desconto em serviço rápido (sobrancelha, manicure). Dois atendimentos extras por quarta podem recuperar parte da queda de fevereiro.",
      "servicos": "A escova caiu 43% em relação a janeiro (R$ 180 vs R$ 315). Clientes de escova têm alta frequência — se sumiram, é sinal de alerta. Ação: identifique as clientes que fizeram escova em janeiro e não voltaram. Um WhatsApp simples com 'Saudade de você!' tem taxa de retorno alta e custo zero.",
      "formas_pagamento": "Fevereiro sem débito — todos pagando em PIX, crédito ou dinheiro. PIX lidera com 59%. Ação: verifique se a máquina de débito está visível e funcionando. Clientes que pagam no débito costumam ser assíduos — não perca esse perfil por falta de maquininha.",
      "faturamento_mes": "Queda de 21% em fevereiro (R$ 2.180 vs R$ 2.760). Isso é sazonalidade — fevereiro é historicamente mais fraco pelo impacto do carnaval na renda. Ação: no próximo ano, prepare antecipadamente uma promoção de fevereiro (ex: combo pré-carnaval) para suavizar a queda.",
      "comparativo_faturamento": "Fevereiro recuou R$ 580 vs janeiro (-21%). Queda de vendas foi maior: -30%. Isso significa atendimentos menores em quantidade, mas com ticket levemente maior. Ação: 4 clientes deixaram de aparecer. Entre em contato com os que estão há mais de 3 semanas sem visita — reativação custa menos que prospectar novo cliente.",
      "ticket_medio_servico": "O ticket médio subiu 12% mesmo com menos vendas (R$ 83,85 vs R$ 74,59). Os clientes que vieram gastaram mais por visita. Ação: mantenha a sugestão de serviços complementares no atendimento — ela está funcionando. Apenas não deixe o ritmo cair com a queda de movimento.",
      "taxa_recorrencia": "22 clientes únicos em fevereiro vs 26 em janeiro — 4 a menos. Ação: crie uma lista no WhatsApp com os clientes que não aparecem há mais de 3 semanas e envie uma mensagem personalizada com uma oferta simples. Reconquistar um cliente existente é 5x mais barato do que atrair um novo."
    }
  },
  "março": {
    "faturamento": 4060.0,
    "vendas": 49,
    "clientes": 23,
    "changeVendas": 88.5,
    "changeFaturamento": 86.2,
    "changeTicket": -1.2,
    "changeClientes": 4.5,
    "servicos": [
      {
        "nome": "progressiva",
        "faturamento": 1440.0
      },
      {
        "nome": "coloração",
        "faturamento": 610.0
      },
      {
        "nome": "coloração + hidratação",
        "faturamento": 400.0
      },
      {
        "nome": "escova",
        "faturamento": 360.0
      },
      {
        "nome": "corte + escova",
        "faturamento": 340.0
      },
      {
        "nome": "hidratação",
        "faturamento": 240.0
      },
      {
        "nome": "manicure + pedicure",
        "faturamento": 220.0
      },
      {
        "nome": "corte",
        "faturamento": 160.0
      },
      {
        "nome": "manicure",
        "faturamento": 120.0
      },
      {
        "nome": "sobrancelha",
        "faturamento": 100.0
      },
      {
        "nome": "corte infantil",
        "faturamento": 70.0
      }
    ],
    "formas_pagamento": [
      {
        "nome": "PIX",
        "valor": 2490.0
      },
      {
        "nome": "CREDITO",
        "valor": 830.0
      },
      {
        "nome": "DINHEIRO",
        "valor": 740.0
      }
    ],
    "atividade_semana": [
      {
        "nome": "Segunda",
        "faturamento": 295.0
      },
      {
        "nome": "Terça",
        "faturamento": 920.0
      },
      {
        "nome": "Quarta",
        "faturamento": 310.0
      },
      {
        "nome": "Quinta",
        "faturamento": 395.0
      },
      {
        "nome": "Sexta",
        "faturamento": 815.0
      },
      {
        "nome": "Sábado",
        "faturamento": 795.0
      },
      {
        "nome": "Domingo",
        "faturamento": 530.0
      }
    ],
    "insights": {
      "atividade_semana": "Terça-feira explodiu para R$ 920 — o maior dia registrado até agora, respondendo por 23% do faturamento do mês. Segunda-feira ainda é o ponto fraco (R$ 295). Ação: agende os serviços premium (Progressiva, Coloração) prioritariamente nas terças e sextas, seus dias mais lucrativos. Reserve segundas para serviços rápidos de fidelização.",
      "servicos": "Progressiva dobrou de valor vs fevereiro (R$ 1.440 vs R$ 720) — crescimento de 100%. A demanda por tratamentos disparou. Ação: garanta estoque suficiente de produtos para progressiva antes do mês seguinte. Ficar sem produto em dia de pico (terça ou sexta) significa perda direta de receita.",
      "formas_pagamento": "PIX dominou com 61% (R$ 2.490) e o volume total quase dobrou. Ação: com esse nível de faturamento, considere abrir uma conta PJ. Isso facilita o controle do negócio, permite emitir nota fiscal e melhora o acesso a crédito caso precise investir no salão.",
      "faturamento_mes": "Março foi o melhor mês até agora: R$ 4.060, crescimento de +86% vs fevereiro. Ação: identifique o que gerou esse salto — foi indicação? divulgação no Instagram? retorno de clientes antigos? Saiba a causa para poder reproduzir nos próximos meses.",
      "comparativo_faturamento": "Crescimento de +86% em março — o maior da série histórica. Atendimentos saltaram de 26 para 49 em um único mês. Ação: anote tudo o que foi feito de diferente em março. Qualquer mudança de comportamento ou divulgação que coincidiu com esse crescimento deve ser mantida ou ampliada.",
      "ticket_medio_servico": "Ticket médio de R$ 82,86 — levemente abaixo de fevereiro, mas com volume muito maior. Ação: com mais atendimentos, adicionar R$ 17 por visita (uma hidratação, sobrancelha ou manicure) levaria o ticket a R$ 100. Isso significa R$ 800 adicionais por mês sem precisar de nenhum cliente novo.",
      "taxa_recorrencia": "23 clientes em março em alta constante desde fevereiro. Ação: março é o momento ideal para lançar um programa de fidelidade. Modelo simples que funciona: 'A cada 5 visitas, você ganha 1 escova grátis.' Isso incentiva retornos frequentes e aumenta o valor de vida do cliente."
    }
  },
  "abril": {
    "faturamento": 4050.0,
    "vendas": 49,
    "clientes": 23,
    "changeVendas": 0.0,
    "changeFaturamento": -0.2,
    "changeTicket": -0.2,
    "changeClientes": 0.0,
    "servicos": [
      {
        "nome": "progressiva",
        "faturamento": 1430.0
      },
      {
        "nome": "coloracao",
        "faturamento": 620.0
      },
      {
        "nome": "coloracao + hidrat",
        "faturamento": 390.0
      },
      {
        "nome": "escova",
        "faturamento": 360.0
      },
      {
        "nome": "corte + escova",
        "faturamento": 340.0
      },
      {
        "nome": "hidratacao",
        "faturamento": 240.0
      },
      {
        "nome": "manicure + pedicure",
        "faturamento": 220.0
      },
      {
        "nome": "corte",
        "faturamento": 160.0
      },
      {
        "nome": "manicure",
        "faturamento": 120.0
      },
      {
        "nome": "sobrancelha",
        "faturamento": 100.0
      },
      {
        "nome": "corte infantil",
        "faturamento": 70.0
      }
    ],
    "formas_pagamento": [
      {
        "nome": "PIX",
        "valor": 2540.0
      },
      {
        "nome": "CREDITO",
        "valor": 770.0
      },
      {
        "nome": "DINHEIRO",
        "valor": 740.0
      }
    ],
    "atividade_semana": [
      {
        "nome": "Segunda",
        "faturamento": 480.0
      },
      {
        "nome": "Terça",
        "faturamento": 835.0
      },
      {
        "nome": "Quarta",
        "faturamento": 640.0
      },
      {
        "nome": "Quinta",
        "faturamento": 495.0
      },
      {
        "nome": "Sexta",
        "faturamento": 660.0
      },
      {
        "nome": "Sábado",
        "faturamento": 480.0
      },
      {
        "nome": "Domingo",
        "faturamento": 460.0
      }
    ],
    "insights": {
      "atividade_semana": "Abril foi o mês mais equilibrado da semana — nenhum dia concentrou mais de 21% do faturamento. Terça lidera (R$ 835), seguida de sexta (R$ 660) e quarta (R$ 640). Ação: com agenda tão bem distribuída, o próximo passo não é mais volume — é aumentar o ticket por atendimento. Ofereça um serviço adicional em cada visita, mesmo que pequeno.",
      "servicos": "O mix de serviços ficou praticamente idêntico a março. Progressiva segue dominando com 35% do faturamento. Ação: tente aumentar a participação de serviços de alta frequência como manicure + pedicure e sobrancelha. Clientes que fazem esses serviços voltam a cada 15 dias — criam um fluxo de caixa mais previsível.",
      "formas_pagamento": "PIX cresceu para 63% do total (R$ 2.540). Crédito caiu levemente. Ação: não desative o cartão de crédito — clientes que pagam no crédito tendem a fazer serviços de maior valor e parcelar. Manter essa opção disponível preserva um perfil importante de cliente.",
      "faturamento_mes": "R$ 4.050 em abril — praticamente estável vs março (-0,2%). O salão consolidou o patamar de R$ 4.000. Ação: para romper essa barreira e crescer, é necessária uma ação ativa. Uma campanha de indicação ('traga uma amiga e ganhe 10% de desconto') pode trazer novos clientes sem custo de mídia.",
      "comparativo_faturamento": "Estabilidade total em relação a março — mesmas 49 vendas, mesmos 23 clientes, faturamento quase idêntico. Ação: estabilidade indica uma base sólida, mas crescer exige esforço. Programa de indicação, parcerias locais (ex: academia, clínica de estética próxima) ou novos serviços são os caminhos mais indicados agora.",
      "ticket_medio_servico": "Ticket médio estável há dois meses (R$ 82,65 em abril vs R$ 82,86 em março). Ação: R$ 17 separam você de um ticket médio de R$ 100. Treine a sugestão de serviços no atendimento: 'Quer aproveitar e fazer a sobrancelha também?' — simples, não invasivo, e aumenta o faturamento sem nenhum custo.",
      "taxa_recorrencia": "Base de 23 clientes fiéis consolidada por dois meses seguidos. Ação: crie uma lista VIP no WhatsApp com esses clientes. Envie ofertas exclusivas para eles antes de abrir para o público geral. Isso aumenta a percepção de valor do salão e fortalece o vínculo com quem já é fiel."
    }
  },
  "maio": {
    "faturamento": 4805.0,
    "vendas": 59,
    "clientes": 26,
    "changeVendas": 20.4,
    "changeFaturamento": 18.6,
    "changeTicket": -1.5,
    "changeClientes": 13.0,
    "servicos": [
      {
        "nome": "progressiva",
        "faturamento": 1830.0
      },
      {
        "nome": "coloracao",
        "faturamento": 750.0
      },
      {
        "nome": "escova",
        "faturamento": 585.0
      },
      {
        "nome": "manicure + pedicure",
        "faturamento": 385.0
      },
      {
        "nome": "corte + escova",
        "faturamento": 345.0
      },
      {
        "nome": "hidratacao",
        "faturamento": 305.0
      },
      {
        "nome": "coloracao + hidrat",
        "faturamento": 200.0
      },
      {
        "nome": "manicure",
        "faturamento": 120.0
      },
      {
        "nome": "corte infantil",
        "faturamento": 105.0
      },
      {
        "nome": "sobrancelha",
        "faturamento": 100.0
      },
      {
        "nome": "corte",
        "faturamento": 80.0
      }
    ],
    "formas_pagamento": [
      {
        "nome": "PIX",
        "valor": 2878.0
      },
      {
        "nome": "DINHEIRO",
        "valor": 977.0
      },
      {
        "nome": "CREDITO",
        "valor": 950.0
      }
    ],
    "atividade_semana": [
      {
        "nome": "Segunda",
        "faturamento": 602.0
      },
      {
        "nome": "Terça",
        "faturamento": 120.0
      },
      {
        "nome": "Quarta",
        "faturamento": 707.0
      },
      {
        "nome": "Quinta",
        "faturamento": 452.0
      },
      {
        "nome": "Sexta",
        "faturamento": 1136.0
      },
      {
        "nome": "Sábado",
        "faturamento": 1141.0
      },
      {
        "nome": "Domingo",
        "faturamento": 647.0
      }
    ],
    "insights": {
      "atividade_semana": "⚠️ Dados estimados — aguardando CSV de maio. Sábado projetado como dia mais forte (R$ 1.141) e terça com anomalia (R$ 120 — provável erro ou dia com poucos registros). Ação: ao processar o CSV real de maio, compare os dias estimados com os reais para calibrar as projeções futuras.",
      "servicos": "⚠️ Dados estimados. Progressiva projetada em R$ 1.648 (+15% vs abril) seguindo a tendência de crescimento. Ação: quando o CSV de maio chegar, rode o processar.py para atualizar todos os dados automaticamente.",
      "formas_pagamento": "⚠️ Dados estimados. PIX projetado como forma dominante continuando a tendência dos meses anteriores. Ação: verifique se os dados reais de maio confirmam o crescimento do PIX — isso indica que sua base de clientes é cada vez mais digital.",
      "faturamento_mes": "⚠️ Dados estimados. Projeção de R$ 4.658 para maio (+15% vs abril). Ação: processe o CSV real de maio assim que disponível. Metas sugeridas para maio: superar R$ 4.500 reais em faturamento e chegar a 25+ clientes únicos.",
      "comparativo_faturamento": "⚠️ Dados estimados. Projeção de crescimento de +15% sobre abril se o ritmo de março e abril se mantiver. Ação: se o crescimento real ficar abaixo da projeção, identifique a causa — foi perda de clientes, menos serviços premium ou dias parados?",
      "ticket_medio_servico": "⚠️ Dados estimados. Projeção de ticket médio levemente abaixo de abril devido ao maior volume de atendimentos. Ação: acompanhe se o mix de serviços em maio mantém a Progressiva como âncora ou se outros serviços ganham espaço.",
      "taxa_recorrencia": "⚠️ Dados estimados. Adicione o CSV de maio para validar a recorrência real de clientes. Ação: verifique quantos dos 23 clientes de abril retornaram em maio — essa taxa de retorno é o melhor indicador de saúde do negócio."
    }
  }
}